sentry_pyodbc/__init__.py
sentry_pyodbc/config.py
sentry_pyodbc/instrumentation.py
sentry_pyodbc/proxy.py
sentry_pyodbc/py.typed
sentry_pyodbc/sanitize.py
sentry_pyodbc/version.py
sentry_pyodbc-0.1.1.dist-info/METADATA
sentry_pyodbc-0.1.1.dist-info/WHEEL
sentry_pyodbc-0.1.1.dist-info/licenses/LICENSE
sentry_pyodbc-0.1.1.dist-info/RECORD
